odoo9_addon_pos_reset_search-9.0.0.0.1.99.dev10-py3.6-nspkg.pth
odoo_addons/pos_reset_search/README.rst
odoo_addons/pos_reset_search/__init__.py
odoo_addons/pos_reset_search/__openerp__.py
odoo_addons/pos_reset_search/i18n/ca.po
odoo_addons/pos_reset_search/i18n/es.po
odoo_addons/pos_reset_search/i18n/pos_reset_search.pot
odoo_addons/pos_reset_search/readme/CONTRIBUTORS.rst
odoo_addons/pos_reset_search/readme/DESCRIPTION.rst
odoo_addons/pos_reset_search/readme/USAGE.rst
odoo_addons/pos_reset_search/static/description/icon.png
odoo_addons/pos_reset_search/static/description/index.html
odoo_addons/pos_reset_search/static/src/js/reset.js
odoo_addons/pos_reset_search/views/templates.xml
odoo9_addon_pos_reset_search-9.0.0.0.1.99.dev10.dist-info/METADATA
odoo9_addon_pos_reset_search-9.0.0.0.1.99.dev10.dist-info/WHEEL
odoo9_addon_pos_reset_search-9.0.0.0.1.99.dev10.dist-info/namespace_packages.txt
odoo9_addon_pos_reset_search-9.0.0.0.1.99.dev10.dist-info/top_level.txt
odoo9_addon_pos_reset_search-9.0.0.0.1.99.dev10.dist-info/RECORD
